resources/__init__.py
shared/__init__.py
ragatanga-0.9.0.dist-info/METADATA
ragatanga-0.9.0.dist-info/WHEEL
ragatanga-0.9.0.dist-info/top_level.txt
ragatanga-0.9.0.dist-info/RECORD
