Metadata-Version: 2.4
Name: ragatanga
Version: 0.9.0
Summary: A comprehensive system for managing ontologies with multi-tenant support, RESTful API, FastMCP integration, and intelligent navigation capabilities
Author-email: Your Name <your.email@example.com>
License-Expression: MIT
Project-URL: Homepage, https://github.com/jquant/ragatanga-mcp
Project-URL: Bug Tracker, https://github.com/jquant/ragatanga-mcp/issues
Keywords: ontology,rdf,sparql,semantic-web,multi-tenant
Classifier: Development Status :: 4 - Beta
Classifier: Intended Audience :: Developers
Classifier: Programming Language :: Python :: 3
Classifier: Programming Language :: Python :: 3.13
Classifier: Topic :: Software Development :: Libraries :: Python Modules
Classifier: Topic :: Internet :: WWW/HTTP :: Dynamic Content
Requires-Python: >=3.13
Requires-Dist: rdflib>=7.1.3
Requires-Dist: ruff>=0.11.2
Requires-Dist: upstash-redis>=1.3.0
Requires-Dist: httpx-sse>=0.4.0
Requires-Dist: sse-starlette>=2.2.1
Requires-Dist: websockets>=12.0
Requires-Dist: pyarrow>=19.0.0
Requires-Dist: modal>=0.73.132
Requires-Dist: openai-agents>=0.0.7
Requires-Dist: logger>=1.4
Requires-Dist: mcp[cli]>=1.6.0
Requires-Dist: python-decouple>=3.8
Requires-Dist: pydantic-settings>=2.8.1
Requires-Dist: pydantic>=2.11.0
Requires-Dist: loguru>=0.7.3
Requires-Dist: python-dotenv>=1.0.0
Provides-Extra: dev
Requires-Dist: pre-commit>=4.2.0; extra == "dev"
Requires-Dist: mypy>=1.9.0; extra == "dev"
Requires-Dist: build>=1.0.3; extra == "dev"
Requires-Dist: twine>=4.0.2; extra == "dev"
